fit/__init__.py
fit/version.py
fit/datamodules/GroundTruthDatasetFactory.py
fit/datamodules/__init__.py
fit/datamodules/super_res/SResDataModule.py
fit/datamodules/super_res/SResFCDataset.py
fit/datamodules/super_res/__init__.py
fit/datamodules/tomo_rec/TRecDataModule.py
fit/datamodules/tomo_rec/TRecFCDataset.py
fit/datamodules/tomo_rec/__init__.py
fit/modules/SResTransformerModule.py
fit/modules/TRecTransformerModule.py
fit/modules/__init__.py
fit/modules/loss.py
fit/transformers/PositionalEncoding2D.py
fit/transformers/SResTransformer.py
fit/transformers/TRecTransformer.py
fit/transformers/__init__.py
fit/utils/RAdam.py
fit/utils/__init__.py
fit/utils/tomo_utils.py
fit/utils/utils.py
fit_tests/__init__.py
fit_tests/utils/__init__.py
fit_tests/utils/test_tomo_utils.py
fit_tests/utils/test_utils.py
fourier_image_transformer-0.2.0.dist-info/LICENSE
fourier_image_transformer-0.2.0.dist-info/METADATA
fourier_image_transformer-0.2.0.dist-info/WHEEL
fourier_image_transformer-0.2.0.dist-info/top_level.txt
fourier_image_transformer-0.2.0.dist-info/RECORD
