Metadata-Version: 2.1
Name: fourier-image-transformer
Version: 0.2.0
Summary: Fourier Image Transformer
Home-page: https://github.com/juglab/FourierImageTransformer/
Author: Tim-Oliver Buchholz, Florian Jug
Author-email: tibuch@mpi-cbg.de, florian.jug@fht.org
License: BSD 3-Clause License
Project-URL: Repository, https://github.com/juglab/FourierImageTransformer/
Platform: UNKNOWN
Classifier: Development Status :: 4 - Beta
Classifier: Intended Audience :: Science/Research
Classifier: Topic :: Scientific/Engineering
Classifier: License :: OSI Approved :: BSD License
Classifier: Programming Language :: Python :: 3.7
Requires-Dist: numpy
Requires-Dist: scipy
Requires-Dist: matplotlib
Requires-Dist: torch (>=1.7.0)
Requires-Dist: torchvision
Requires-Dist: tifffile
Requires-Dist: tqdm
Requires-Dist: pytorch-fast-transformers
Requires-Dist: dival (<0.6.0)
Requires-Dist: pytorch-lightning
Requires-Dist: jupyter
Requires-Dist: wget
